<?xml version="1.0" encoding="utf-8"?>
<clothing-items>
 <clothing>
  <id>
   654597671
  </id>
  <name>
   New Balance Hat O-7656
  </name>
  <category>
   Hat
  </category>
  <size>
   XL
  </size>
  <color>
   Оранжевый
  </color>
  <material>
   Кожа
  </material>
  <price>
   816697
  </price>
  <rating>
   4.39
  </rating>
  <reviews>
   525225
  </reviews>
  <exclusive>
   no
  </exclusive>
  <sporty>
   yes
  </sporty>
 </clothing>
 <clothing>
  <id>
   361161414
  </id>
  <name>
   Puma Jeans S-8863
  </name>
  <category>
   Jeans
  </category>
  <size>
   M
  </size>
  <color>
   Зеленый
  </color>
  <material>
   Хлопок
  </material>
  <price>
   365794
  </price>
  <rating>
   2.57
  </rating>
  <reviews>
   431707
  </reviews>
  <new>
   -
  </new>
  <exclusive>
   no
  </exclusive>
 </clothing>
 <clothing>
  <id>
   835986543
  </id>
  <name>
   Addidas Dress G-2609
  </name>
  <category>
   Dress
  </category>
  <size>
   L
  </size>
  <color>
   Синий
  </color>
  <material>
   Вискоза
  </material>
  <price>
   361829
  </price>
  <rating>
   3.17
  </rating>
  <reviews>
   59883
  </reviews>
  <new>
   +
  </new>
  <exclusive>
   yes
  </exclusive>
 </clothing>
 <clothing>
  <id>
   449044389
  </id>
  <name>
   Nike Shirt C-9140
  </name>
  <category>
   Shirt
  </category>
  <size>
   L
  </size>
  <color>
   Зеленый
  </color>
  <material>
   Хлопок
  </material>
  <price>
   703793
  </price>
  <rating>
   3.3
  </rating>
  <reviews>
   334186
  </reviews>
  <exclusive>
   no
  </exclusive>
 </clothing>
 <clothing>
  <id>
   540871612
  </id>
  <name>
   PleinSport Dress F-8756
  </name>
  <category>
   Dress
  </category>
  <size>
   M
  </size>
  <color>
   Красный
  </color>
  <material>
   Хлопок
  </material>
  <price>
   157468
  </price>
  <rating>
   4.38
  </rating>
  <reviews>
   792871
  </reviews>
  <sporty>
   no
  </sporty>
 </clothing>
 <clothing>
  <id>
   361542978
  </id>
  <name>
   Adidas Handbags T-7407
  </name>
  <category>
   Handbags
  </category>
  <size>
   L
  </size>
  <color>
   Голубой
  </color>
  <material>
   Нейлон
  </material>
  <price>
   312175
  </price>
  <rating>
   1.39
  </rating>
  <reviews>
   363618
  </reviews>
  <exclusive>
   no
  </exclusive>
 </clothing>
 <clothing>
  <id>
   550119735
  </id>
  <name>
   PleinSport Belts J-9384
  </name>
  <category>
   Belts
  </category>
  <size>
   XL
  </size>
  <color>
   Фиолетовый
  </color>
  <material>
   Кожа
  </material>
  <price>
   903864
  </price>
  <rating>
   3.72
  </rating>
  <reviews>
   480124
  </reviews>
  <new>
   +
  </new>
  <exclusive>
   yes
  </exclusive>
 </clothing>
 <clothing>
  <id>
   951285235
  </id>
  <name>
   Converse Shoes U-3257
  </name>
  <category>
   Shoes
  </category>
  <size>
   S
  </size>
  <color>
   Зеленый
  </color>
  <material>
   Шерсть
  </material>
  <price>
   269072
  </price>
  <rating>
   1.2
  </rating>
  <reviews>
   35018
  </reviews>
  <new>
   -
  </new>
 </clothing>
 <clothing>
  <id>
   490128568
  </id>
  <name>
   Lacoste Pants S-7309
  </name>
  <category>
   Pants
  </category>
  <size>
   M
  </size>
  <color>
   Зеленый
  </color>
  <material>
   Кожа
  </material>
  <price>
   573766
  </price>
  <rating>
   4.38
  </rating>
  <reviews>
   91534
  </reviews>
  <sporty>
   no
  </sporty>
 </clothing>
 <clothing>
  <id>
   161344661
  </id>
  <name>
   Vans Sweater A-8756
  </name>
  <category>
   Sweater
  </category>
  <size>
   XXL
  </size>
  <color>
   Зеленый
  </color>
  <material>
   Вискоза
  </material>
  <price>
   857456
  </price>
  <rating>
   3.05
  </rating>
  <reviews>
   50224
  </reviews>
  <new>
   -
  </new>
  <exclusive>
   no
  </exclusive>
  <sporty>
   no
  </sporty>
 </clothing>
 <clothing>
  <id>
   932224750
  </id>
  <name>
   Converse Pants I-1747
  </name>
  <category>
   Pants
  </category>
  <size>
   S
  </size>
  <color>
   Красный
  </color>
  <material>
   Полиэстер
  </material>
  <price>
   440533
  </price>
  <rating>
   1.35
  </rating>
  <reviews>
   847809
  </reviews>
  <new>
   +
  </new>
  <exclusive>
   yes
  </exclusive>
  <sporty>
   yes
  </sporty>
 </clothing>
 <clothing>
  <id>
   678185915
  </id>
  <name>
   Converse Umbrellas B-6067
  </name>
  <category>
   Umbrellas
  </category>
  <size>
   XL
  </size>
  <color>
   Красный
  </color>
  <material>
   Кожа
  </material>
  <price>
   536693
  </price>
  <rating>
   2.25
  </rating>
  <reviews>
   223877
  </reviews>
  <new>
   +
  </new>
 </clothing>
 <clothing>
  <id>
   479691480
  </id>
  <name>
   Adidas Jeans U-4005
  </name>
  <category>
   Jeans
  </category>
  <size>
   XXL
  </size>
  <color>
   Зеленый
  </color>
  <material>
   Хлопок
  </material>
  <price>
   729090
  </price>
  <rating>
   2.97
  </rating>
  <reviews>
   417711
  </reviews>
  <new>
   -
  </new>
  <exclusive>
   yes
  </exclusive>
  <sporty>
   no
  </sporty>
 </clothing>
 <clothing>
  <id>
   195868071
  </id>
  <name>
   Lacoste Socks A-8561
  </name>
  <category>
   Socks
  </category>
  <size>
   M
  </size>
  <color>
   Зеленый
  </color>
  <material>
   Хлопок
  </material>
  <price>
   272151
  </price>
  <rating>
   2.47
  </rating>
  <reviews>
   400515
  </reviews>
  <new>
   -
  </new>
  <exclusive>
   no
  </exclusive>
  <sporty>
   yes
  </sporty>
 </clothing>
 <clothing>
  <id>
   760922457
  </id>
  <name>
   Adidas Sweater F-6008
  </name>
  <category>
   Sweater
  </category>
  <size>
   S
  </size>
  <color>
   Синий
  </color>
  <material>
   Шелк
  </material>
  <price>
   306455
  </price>
  <rating>
   2.35
  </rating>
  <reviews>
   664273
  </reviews>
 </clothing>
 <clothing>
  <id>
   634296519
  </id>
  <name>
   Vans Handbags L-7059
  </name>
  <category>
   Handbags
  </category>
  <size>
   M
  </size>
  <color>
   Голубой
  </color>
  <material>
   Нейлон
  </material>
  <price>
   324183
  </price>
  <rating>
   4.45
  </rating>
  <reviews>
   150576
  </reviews>
  <exclusive>
   yes
  </exclusive>
  <sporty>
   yes
  </sporty>
 </clothing>
 <clothing>
  <id>
   271029796
  </id>
  <name>
   Under Armour Dress M-2584
  </name>
  <category>
   Dress
  </category>
  <size>
   XL
  </size>
  <color>
   Зеленый
  </color>
  <material>
   Шелк
  </material>
  <price>
   401638
  </price>
  <rating>
   1.73
  </rating>
  <reviews>
   78499
  </reviews>
  <exclusive>
   no
  </exclusive>
  <sporty>
   no
  </sporty>
 </clothing>
 <clothing>
  <id>
   695725920
  </id>
  <name>
   New Balance Shoes R-7112
  </name>
  <category>
   Shoes
  </category>
  <size>
   XL
  </size>
  <color>
   Фиолетовый
  </color>
  <material>
   Шелк
  </material>
  <price>
   611932
  </price>
  <rating>
   3.7
  </rating>
  <reviews>
   293038
  </reviews>
 </clothing>
 <clothing>
  <id>
   828798079
  </id>
  <name>
   Reebok Belts N-8895
  </name>
  <category>
   Belts
  </category>
  <size>
   L
  </size>
  <color>
   Синий
  </color>
  <material>
   Хлопок
  </material>
  <price>
   182743
  </price>
  <rating>
   3.61
  </rating>
  <reviews>
   383316
  </reviews>
  <exclusive>
   yes
  </exclusive>
  <sporty>
   no
  </sporty>
 </clothing>
 <clothing>
  <id>
   827072044
  </id>
  <name>
   DC Shoes W-1113
  </name>
  <category>
   Shoes
  </category>
  <size>
   S
  </size>
  <color>
   Синий
  </color>
  <material>
   Кожа
  </material>
  <price>
   990313
  </price>
  <rating>
   3.09
  </rating>
  <reviews>
   505758
  </reviews>
  <new>
   -
  </new>
  <exclusive>
   yes
  </exclusive>
 </clothing>
 <clothing>
  <id>
   650976614
  </id>
  <name>
   Fila Sweater A-2819
  </name>
  <category>
   Sweater
  </category>
  <size>
   XXL
  </size>
  <color>
   Оранжевый
  </color>
  <material>
   Шерсть
  </material>
  <price>
   527298
  </price>
  <rating>
   1.84
  </rating>
  <reviews>
   602538
  </reviews>
  <exclusive>
   no
  </exclusive>
  <sporty>
   no
  </sporty>
 </clothing>
 <clothing>
  <id>
   122749198
  </id>
  <name>
   Ellesse Shoes D-2941
  </name>
  <category>
   Shoes
  </category>
  <size>
   S
  </size>
  <color>
   Синий
  </color>
  <material>
   Нейлон
  </material>
  <price>
   312026
  </price>
  <rating>
   4.41
  </rating>
  <reviews>
   812882
  </reviews>
  <new>
   -
  </new>
  <exclusive>
   yes
  </exclusive>
  <sporty>
   yes
  </sporty>
 </clothing>
 <clothing>
  <id>
   473329013
  </id>
  <name>
   Converse Jeans H-1795
  </name>
  <category>
   Jeans
  </category>
  <size>
   XXL
  </size>
  <color>
   Голубой
  </color>
  <material>
   Шелк
  </material>
  <price>
   253270
  </price>
  <rating>
   3.06
  </rating>
  <reviews>
   366888
  </reviews>
  <new>
   +
  </new>
  <exclusive>
   no
  </exclusive>
 </clothing>
 <clothing>
  <id>
   235688841
  </id>
  <name>
   Nike Gloves J-6526
  </name>
  <category>
   Gloves
  </category>
  <size>
   XL
  </size>
  <color>
   Зеленый
  </color>
  <material>
   Шерсть
  </material>
  <price>
   584889
  </price>
  <rating>
   4.37
  </rating>
  <reviews>
   123874
  </reviews>
  <new>
   -
  </new>
  <exclusive>
   yes
  </exclusive>
 </clothing>
 <clothing>
  <id>
   101147979
  </id>
  <name>
   Vans Dress P-1958
  </name>
  <category>
   Dress
  </category>
  <size>
   XL
  </size>
  <color>
   Оранжевый
  </color>
  <material>
   Кожа
  </material>
  <price>
   560274
  </price>
  <rating>
   1.39
  </rating>
  <reviews>
   809338
  </reviews>
  <exclusive>
   no
  </exclusive>
  <sporty>
   no
  </sporty>
 </clothing>
 <clothing>
  <id>
   166293429
  </id>
  <name>
   Nike T-shirt K-8244
  </name>
  <category>
   T-shirt
  </category>
  <size>
   M
  </size>
  <color>
   Голубой
  </color>
  <material>
   Хлопок
  </material>
  <price>
   585479
  </price>
  <rating>
   1.3
  </rating>
  <reviews>
   154035
  </reviews>
  <new>
   +
  </new>
  <sporty>
   yes
  </sporty>
 </clothing>
 <clothing>
  <id>
   522800095
  </id>
  <name>
   DC Blouse Y-8391
  </name>
  <category>
   Blouse
  </category>
  <size>
   XXL
  </size>
  <color>
   Красный
  </color>
  <material>
   Кожа
  </material>
  <price>
   831601
  </price>
  <rating>
   1.87
  </rating>
  <reviews>
   797700
  </reviews>
  <new>
   -
  </new>
  <exclusive>
   yes
  </exclusive>
 </clothing>
 <clothing>
  <id>
   112060551
  </id>
  <name>
   Converse Pants V-2798
  </name>
  <category>
   Pants
  </category>
  <size>
   XL
  </size>
  <color>
   Зеленый
  </color>
  <material>
   Кожа
  </material>
  <price>
   579888
  </price>
  <rating>
   4.29
  </rating>
  <reviews>
   324607
  </reviews>
  <new>
   -
  </new>
  <sporty>
   yes
  </sporty>
 </clothing>
 <clothing>
  <id>
   532208305
  </id>
  <name>
   Brooks Gloves H-2318
  </name>
  <category>
   Gloves
  </category>
  <size>
   XXL
  </size>
  <color>
   Фиолетовый
  </color>
  <material>
   Лен
  </material>
  <price>
   842855
  </price>
  <rating>
   2.1
  </rating>
  <reviews>
   192198
  </reviews>
  <new>
   -
  </new>
 </clothing>
 <clothing>
  <id>
   939624452
  </id>
  <name>
   Ellesse Blouse G-3223
  </name>
  <category>
   Blouse
  </category>
  <size>
   L
  </size>
  <color>
   Голубой
  </color>
  <material>
   Шелк
  </material>
  <price>
   416955
  </price>
  <rating>
   2.51
  </rating>
  <reviews>
   146514
  </reviews>
  <new>
   -
  </new>
 </clothing>
 <clothing>
  <id>
   811424717
  </id>
  <name>
   Under Armour Umbrellas B-9451
  </name>
  <category>
   Umbrellas
  </category>
  <size>
   L
  </size>
  <color>
   Синий
  </color>
  <material>
   Нейлон
  </material>
  <price>
   931172
  </price>
  <rating>
   1.81
  </rating>
  <reviews>
   386834
  </reviews>
  <exclusive>
   yes
  </exclusive>
 </clothing>
 <clothing>
  <id>
   998166604
  </id>
  <name>
   Converse T-shirt I-9265
  </name>
  <category>
   T-shirt
  </category>
  <size>
   XL
  </size>
  <color>
   Голубой
  </color>
  <material>
   Кожа
  </material>
  <price>
   166878
  </price>
  <rating>
   4.46
  </rating>
  <reviews>
   652175
  </reviews>
  <new>
   +
  </new>
  <exclusive>
   yes
  </exclusive>
  <sporty>
   yes
  </sporty>
 </clothing>
 <clothing>
  <id>
   178204954
  </id>
  <name>
   Reebok Hat T-7544
  </name>
  <category>
   Hat
  </category>
  <size>
   L
  </size>
  <color>
   Оранжевый
  </color>
  <material>
   Нейлон
  </material>
  <price>
   424178
  </price>
  <rating>
   1.11
  </rating>
  <reviews>
   333008
  </reviews>
  <new>
   -
  </new>
  <sporty>
   no
  </sporty>
 </clothing>
 <clothing>
  <id>
   998919198
  </id>
  <name>
   New Balance Shirt Y-9071
  </name>
  <category>
   Shirt
  </category>
  <size>
   M
  </size>
  <color>
   Оранжевый
  </color>
  <material>
   Нейлон
  </material>
  <price>
   621413
  </price>
  <rating>
   4.62
  </rating>
  <reviews>
   236752
  </reviews>
  <exclusive>
   yes
  </exclusive>
  <sporty>
   no
  </sporty>
 </clothing>
 <clothing>
  <id>
   523565383
  </id>
  <name>
   Converse Hat X-2533
  </name>
  <category>
   Hat
  </category>
  <size>
   XXL
  </size>
  <color>
   Синий
  </color>
  <material>
   Шелк
  </material>
  <price>
   517551
  </price>
  <rating>
   2.92
  </rating>
  <reviews>
   12835
  </reviews>
  <new>
   -
  </new>
  <exclusive>
   no
  </exclusive>
  <sporty>
   no
  </sporty>
 </clothing>
 <clothing>
  <id>
   158360381
  </id>
  <name>
   Adidas T-shirt Y-2873
  </name>
  <category>
   T-shirt
  </category>
  <size>
   XL
  </size>
  <color>
   Оранжевый
  </color>
  <material>
   Хлопок
  </material>
  <price>
   762916
  </price>
  <rating>
   4.93
  </rating>
  <reviews>
   673924
  </reviews>
  <new>
   -
  </new>
  <exclusive>
   no
  </exclusive>
  <sporty>
   yes
  </sporty>
 </clothing>
</clothing-items>
