<?xml version="1.0" encoding="utf-8"?>
<clothing-items>
 <clothing>
  <id>
   296766203
  </id>
  <name>
   Asics T-shirt B-2794
  </name>
  <category>
   T-shirt
  </category>
  <size>
   S
  </size>
  <color>
   Желтый
  </color>
  <material>
   Хлопок
  </material>
  <price>
   925769
  </price>
  <rating>
   4.15
  </rating>
  <reviews>
   783463
  </reviews>
  <new>
   -
  </new>
  <sporty>
   no
  </sporty>
 </clothing>
 <clothing>
  <id>
   958705713
  </id>
  <name>
   Nike Handbags Y-4522
  </name>
  <category>
   Handbags
  </category>
  <size>
   S
  </size>
  <color>
   Желтый
  </color>
  <material>
   Шерсть
  </material>
  <price>
   258272
  </price>
  <rating>
   1.37
  </rating>
  <reviews>
   31545
  </reviews>
  <new>
   -
  </new>
  <sporty>
   yes
  </sporty>
 </clothing>
 <clothing>
  <id>
   549522166
  </id>
  <name>
   Nike Shoes X-5978
  </name>
  <category>
   Shoes
  </category>
  <size>
   M
  </size>
  <color>
   Красный
  </color>
  <material>
   Нейлон
  </material>
  <price>
   717291
  </price>
  <rating>
   1.19
  </rating>
  <reviews>
   389316
  </reviews>
  <sporty>
   no
  </sporty>
 </clothing>
 <clothing>
  <id>
   257582611
  </id>
  <name>
   New Balance Handbags C-9318
  </name>
  <category>
   Handbags
  </category>
  <size>
   M
  </size>
  <color>
   Фиолетовый
  </color>
  <material>
   Вискоза
  </material>
  <price>
   766828
  </price>
  <rating>
   4.27
  </rating>
  <reviews>
   468511
  </reviews>
  <new>
   -
  </new>
 </clothing>
 <clothing>
  <id>
   463753405
  </id>
  <name>
   Reebok T-shirt V-8626
  </name>
  <category>
   T-shirt
  </category>
  <size>
   S
  </size>
  <color>
   Оранжевый
  </color>
  <material>
   Шерсть
  </material>
  <price>
   284773
  </price>
  <rating>
   4.84
  </rating>
  <reviews>
   824220
  </reviews>
  <new>
   -
  </new>
  <sporty>
   no
  </sporty>
 </clothing>
 <clothing>
  <id>
   950779792
  </id>
  <name>
   Under Armour T-shirt O-1156
  </name>
  <category>
   T-shirt
  </category>
  <size>
   M
  </size>
  <color>
   Фиолетовый
  </color>
  <material>
   Вискоза
  </material>
  <price>
   828821
  </price>
  <rating>
   1.9
  </rating>
  <reviews>
   955828
  </reviews>
  <exclusive>
   yes
  </exclusive>
 </clothing>
 <clothing>
  <id>
   567504697
  </id>
  <name>
   Asics Gloves W-6216
  </name>
  <category>
   Gloves
  </category>
  <size>
   XL
  </size>
  <color>
   Фиолетовый
  </color>
  <material>
   Лен
  </material>
  <price>
   131444
  </price>
  <rating>
   4.5
  </rating>
  <reviews>
   147760
  </reviews>
  <exclusive>
   no
  </exclusive>
  <sporty>
   yes
  </sporty>
 </clothing>
 <clothing>
  <id>
   627445784
  </id>
  <name>
   Addidas Socks O-5965
  </name>
  <category>
   Socks
  </category>
  <size>
   L
  </size>
  <color>
   Фиолетовый
  </color>
  <material>
   Шелк
  </material>
  <price>
   758373
  </price>
  <rating>
   4.88
  </rating>
  <reviews>
   495479
  </reviews>
 </clothing>
 <clothing>
  <id>
   750181389
  </id>
  <name>
   Converse Umbrellas F-4953
  </name>
  <category>
   Umbrellas
  </category>
  <size>
   XXL
  </size>
  <color>
   Фиолетовый
  </color>
  <material>
   Шелк
  </material>
  <price>
   404139
  </price>
  <rating>
   3.18
  </rating>
  <reviews>
   474225
  </reviews>
  <new>
   -
  </new>
  <exclusive>
   yes
  </exclusive>
  <sporty>
   no
  </sporty>
 </clothing>
 <clothing>
  <id>
   892531813
  </id>
  <name>
   Addidas Skirt C-6324
  </name>
  <category>
   Skirt
  </category>
  <size>
   M
  </size>
  <color>
   Голубой
  </color>
  <material>
   Кожа
  </material>
  <price>
   849234
  </price>
  <rating>
   2.53
  </rating>
  <reviews>
   239182
  </reviews>
  <new>
   -
  </new>
  <exclusive>
   no
  </exclusive>
 </clothing>
 <clothing>
  <id>
   289017479
  </id>
  <name>
   DC Jeans U-4387
  </name>
  <category>
   Jeans
  </category>
  <size>
   XL
  </size>
  <color>
   Оранжевый
  </color>
  <material>
   Шерсть
  </material>
  <price>
   865672
  </price>
  <rating>
   3.25
  </rating>
  <reviews>
   973159
  </reviews>
  <exclusive>
   no
  </exclusive>
  <sporty>
   no
  </sporty>
 </clothing>
 <clothing>
  <id>
   508899029
  </id>
  <name>
   Converse Umbrellas S-1734
  </name>
  <category>
   Umbrellas
  </category>
  <size>
   M
  </size>
  <color>
   Зеленый
  </color>
  <material>
   Хлопок
  </material>
  <price>
   974646
  </price>
  <rating>
   3.03
  </rating>
  <reviews>
   211557
  </reviews>
  <new>
   +
  </new>
  <exclusive>
   no
  </exclusive>
  <sporty>
   no
  </sporty>
 </clothing>
 <clothing>
  <id>
   179539156
  </id>
  <name>
   Converse Skirt W-1942
  </name>
  <category>
   Skirt
  </category>
  <size>
   S
  </size>
  <color>
   Голубой
  </color>
  <material>
   Полиэстер
  </material>
  <price>
   667042
  </price>
  <rating>
   4.26
  </rating>
  <reviews>
   720082
  </reviews>
  <new>
   +
  </new>
  <exclusive>
   yes
  </exclusive>
  <sporty>
   no
  </sporty>
 </clothing>
 <clothing>
  <id>
   422215851
  </id>
  <name>
   Addidas Shirt W-7931
  </name>
  <category>
   Shirt
  </category>
  <size>
   M
  </size>
  <color>
   Синий
  </color>
  <material>
   Хлопок
  </material>
  <price>
   624975
  </price>
  <rating>
   1.65
  </rating>
  <reviews>
   60597
  </reviews>
  <sporty>
   no
  </sporty>
 </clothing>
 <clothing>
  <id>
   520218989
  </id>
  <name>
   Puma Shoes W-4193
  </name>
  <category>
   Shoes
  </category>
  <size>
   L
  </size>
  <color>
   Синий
  </color>
  <material>
   Полиэстер
  </material>
  <price>
   717470
  </price>
  <rating>
   4.32
  </rating>
  <reviews>
   732024
  </reviews>
  <new>
   -
  </new>
  <sporty>
   no
  </sporty>
 </clothing>
 <clothing>
  <id>
   993260201
  </id>
  <name>
   Brooks T-shirt O-7543
  </name>
  <category>
   T-shirt
  </category>
  <size>
   M
  </size>
  <color>
   Желтый
  </color>
  <material>
   Нейлон
  </material>
  <price>
   915024
  </price>
  <rating>
   2.73
  </rating>
  <reviews>
   156517
  </reviews>
  <exclusive>
   no
  </exclusive>
  <sporty>
   yes
  </sporty>
 </clothing>
 <clothing>
  <id>
   597162031
  </id>
  <name>
   New Balance Shirt G-8365
  </name>
  <category>
   Shirt
  </category>
  <size>
   L
  </size>
  <color>
   Синий
  </color>
  <material>
   Вискоза
  </material>
  <price>
   897498
  </price>
  <rating>
   1.52
  </rating>
  <reviews>
   820343
  </reviews>
  <new>
   +
  </new>
  <sporty>
   no
  </sporty>
 </clothing>
 <clothing>
  <id>
   376418736
  </id>
  <name>
   Fila Socks J-4431
  </name>
  <category>
   Socks
  </category>
  <size>
   XXL
  </size>
  <color>
   Зеленый
  </color>
  <material>
   Шелк
  </material>
  <price>
   283130
  </price>
  <rating>
   1.25
  </rating>
  <reviews>
   16207
  </reviews>
  <exclusive>
   no
  </exclusive>
 </clothing>
 <clothing>
  <id>
   738019992
  </id>
  <name>
   Fila Shirt I-8494
  </name>
  <category>
   Shirt
  </category>
  <size>
   M
  </size>
  <color>
   Фиолетовый
  </color>
  <material>
   Нейлон
  </material>
  <price>
   469803
  </price>
  <rating>
   3.25
  </rating>
  <reviews>
   290643
  </reviews>
  <new>
   +
  </new>
  <sporty>
   no
  </sporty>
 </clothing>
 <clothing>
  <id>
   781992485
  </id>
  <name>
   Vans Handbags A-7430
  </name>
  <category>
   Handbags
  </category>
  <size>
   XXL
  </size>
  <color>
   Голубой
  </color>
  <material>
   Вискоза
  </material>
  <price>
   751834
  </price>
  <rating>
   1.99
  </rating>
  <reviews>
   104075
  </reviews>
  <exclusive>
   yes
  </exclusive>
  <sporty>
   no
  </sporty>
 </clothing>
 <clothing>
  <id>
   388891955
  </id>
  <name>
   Vans Dress O-3913
  </name>
  <category>
   Dress
  </category>
  <size>
   M
  </size>
  <color>
   Желтый
  </color>
  <material>
   Полиэстер
  </material>
  <price>
   302403
  </price>
  <rating>
   1.72
  </rating>
  <reviews>
   576576
  </reviews>
  <new>
   +
  </new>
  <exclusive>
   no
  </exclusive>
  <sporty>
   yes
  </sporty>
 </clothing>
 <clothing>
  <id>
   909985827
  </id>
  <name>
   Asics Shirt J-5427
  </name>
  <category>
   Shirt
  </category>
  <size>
   XL
  </size>
  <color>
   Фиолетовый
  </color>
  <material>
   Шерсть
  </material>
  <price>
   192779
  </price>
  <rating>
   3.98
  </rating>
  <reviews>
   667871
  </reviews>
  <new>
   -
  </new>
  <sporty>
   yes
  </sporty>
 </clothing>
 <clothing>
  <id>
   566241222
  </id>
  <name>
   Ellesse Shoes E-7182
  </name>
  <category>
   Shoes
  </category>
  <size>
   S
  </size>
  <color>
   Зеленый
  </color>
  <material>
   Шелк
  </material>
  <price>
   270481
  </price>
  <rating>
   1.33
  </rating>
  <reviews>
   75626
  </reviews>
  <new>
   -
  </new>
  <exclusive>
   no
  </exclusive>
  <sporty>
   no
  </sporty>
 </clothing>
 <clothing>
  <id>
   261448217
  </id>
  <name>
   Nike Skirt Y-9354
  </name>
  <category>
   Skirt
  </category>
  <size>
   S
  </size>
  <color>
   Желтый
  </color>
  <material>
   Нейлон
  </material>
  <price>
   162351
  </price>
  <rating>
   3.1
  </rating>
  <reviews>
   347817
  </reviews>
 </clothing>
 <clothing>
  <id>
   571503451
  </id>
  <name>
   Addidas T-shirt T-9615
  </name>
  <category>
   T-shirt
  </category>
  <size>
   S
  </size>
  <color>
   Зеленый
  </color>
  <material>
   Полиэстер
  </material>
  <price>
   994881
  </price>
  <rating>
   2.7
  </rating>
  <reviews>
   7285
  </reviews>
 </clothing>
 <clothing>
  <id>
   989216522
  </id>
  <name>
   Nike Blouse I-1000
  </name>
  <category>
   Blouse
  </category>
  <size>
   M
  </size>
  <color>
   Синий
  </color>
  <material>
   Вискоза
  </material>
  <price>
   650874
  </price>
  <rating>
   2.66
  </rating>
  <reviews>
   593457
  </reviews>
  <new>
   -
  </new>
  <exclusive>
   no
  </exclusive>
  <sporty>
   no
  </sporty>
 </clothing>
 <clothing>
  <id>
   299445943
  </id>
  <name>
   Asics Umbrellas G-1239
  </name>
  <category>
   Umbrellas
  </category>
  <size>
   XL
  </size>
  <color>
   Синий
  </color>
  <material>
   Лен
  </material>
  <price>
   485862
  </price>
  <rating>
   2.44
  </rating>
  <reviews>
   119941
  </reviews>
  <sporty>
   no
  </sporty>
 </clothing>
 <clothing>
  <id>
   490941346
  </id>
  <name>
   Converse T-shirt S-1189
  </name>
  <category>
   T-shirt
  </category>
  <size>
   XXL
  </size>
  <color>
   Оранжевый
  </color>
  <material>
   Лен
  </material>
  <price>
   399383
  </price>
  <rating>
   1.84
  </rating>
  <reviews>
   997310
  </reviews>
 </clothing>
 <clothing>
  <id>
   994791693
  </id>
  <name>
   Asics Jacket V-4056
  </name>
  <category>
   Jacket
  </category>
  <size>
   L
  </size>
  <color>
   Синий
  </color>
  <material>
   Шерсть
  </material>
  <price>
   991769
  </price>
  <rating>
   3.82
  </rating>
  <reviews>
   629973
  </reviews>
  <exclusive>
   yes
  </exclusive>
  <sporty>
   no
  </sporty>
 </clothing>
 <clothing>
  <id>
   289146655
  </id>
  <name>
   Fila Handbags F-9930
  </name>
  <category>
   Handbags
  </category>
  <size>
   L
  </size>
  <color>
   Фиолетовый
  </color>
  <material>
   Нейлон
  </material>
  <price>
   610832
  </price>
  <rating>
   4.41
  </rating>
  <reviews>
   938198
  </reviews>
  <sporty>
   yes
  </sporty>
 </clothing>
 <clothing>
  <id>
   884407268
  </id>
  <name>
   Under Armour Socks N-5453
  </name>
  <category>
   Socks
  </category>
  <size>
   L
  </size>
  <color>
   Красный
  </color>
  <material>
   Лен
  </material>
  <price>
   286364
  </price>
  <rating>
   2.98
  </rating>
  <reviews>
   289785
  </reviews>
  <new>
   +
  </new>
  <exclusive>
   no
  </exclusive>
  <sporty>
   no
  </sporty>
 </clothing>
 <clothing>
  <id>
   111589727
  </id>
  <name>
   Addidas Skirt F-7020
  </name>
  <category>
   Skirt
  </category>
  <size>
   S
  </size>
  <color>
   Желтый
  </color>
  <material>
   Нейлон
  </material>
  <price>
   197731
  </price>
  <rating>
   3.18
  </rating>
  <reviews>
   571375
  </reviews>
  <sporty>
   yes
  </sporty>
 </clothing>
 <clothing>
  <id>
   966713439
  </id>
  <name>
   Puma Pants Y-7390
  </name>
  <category>
   Pants
  </category>
  <size>
   XXL
  </size>
  <color>
   Голубой
  </color>
  <material>
   Шелк
  </material>
  <price>
   489910
  </price>
  <rating>
   2.61
  </rating>
  <reviews>
   287617
  </reviews>
  <new>
   -
  </new>
  <exclusive>
   no
  </exclusive>
 </clothing>
 <clothing>
  <id>
   562776670
  </id>
  <name>
   Nike Handbags E-3725
  </name>
  <category>
   Handbags
  </category>
  <size>
   M
  </size>
  <color>
   Синий
  </color>
  <material>
   Хлопок
  </material>
  <price>
   271357
  </price>
  <rating>
   3.05
  </rating>
  <reviews>
   53429
  </reviews>
  <new>
   -
  </new>
  <exclusive>
   no
  </exclusive>
  <sporty>
   no
  </sporty>
 </clothing>
 <clothing>
  <id>
   137381633
  </id>
  <name>
   Nike Socks E-4247
  </name>
  <category>
   Socks
  </category>
  <size>
   L
  </size>
  <color>
   Красный
  </color>
  <material>
   Нейлон
  </material>
  <price>
   170835
  </price>
  <rating>
   1.22
  </rating>
  <reviews>
   604210
  </reviews>
  <exclusive>
   yes
  </exclusive>
 </clothing>
 <clothing>
  <id>
   360764626
  </id>
  <name>
   DC Hat X-5166
  </name>
  <category>
   Hat
  </category>
  <size>
   XXL
  </size>
  <color>
   Фиолетовый
  </color>
  <material>
   Шелк
  </material>
  <price>
   673712
  </price>
  <rating>
   4.93
  </rating>
  <reviews>
   244288
  </reviews>
  <new>
   +
  </new>
  <exclusive>
   yes
  </exclusive>
 </clothing>
 <clothing>
  <id>
   906531940
  </id>
  <name>
   Reebok Hat F-6854
  </name>
  <category>
   Hat
  </category>
  <size>
   XXL
  </size>
  <color>
   Фиолетовый
  </color>
  <material>
   Вискоза
  </material>
  <price>
   719403
  </price>
  <rating>
   4.86
  </rating>
  <reviews>
   342172
  </reviews>
  <new>
   +
  </new>
  <sporty>
   no
  </sporty>
 </clothing>
 <clothing>
  <id>
   120474114
  </id>
  <name>
   Converse Shoes C-4536
  </name>
  <category>
   Shoes
  </category>
  <size>
   XXL
  </size>
  <color>
   Синий
  </color>
  <material>
   Лен
  </material>
  <price>
   140326
  </price>
  <rating>
   4.79
  </rating>
  <reviews>
   318735
  </reviews>
  <new>
   -
  </new>
 </clothing>
 <clothing>
  <id>
   331981289
  </id>
  <name>
   New Balance Hat F-4157
  </name>
  <category>
   Hat
  </category>
  <size>
   XL
  </size>
  <color>
   Красный
  </color>
  <material>
   Шерсть
  </material>
  <price>
   138007
  </price>
  <rating>
   2.02
  </rating>
  <reviews>
   892362
  </reviews>
  <sporty>
   no
  </sporty>
 </clothing>
 <clothing>
  <id>
   658605912
  </id>
  <name>
   Puma Jeans K-6340
  </name>
  <category>
   Jeans
  </category>
  <size>
   M
  </size>
  <color>
   Зеленый
  </color>
  <material>
   Шелк
  </material>
  <price>
   306808
  </price>
  <rating>
   1.59
  </rating>
  <reviews>
   586459
  </reviews>
  <new>
   -
  </new>
 </clothing>
 <clothing>
  <id>
   403236140
  </id>
  <name>
   New Balance Handbags H-2356
  </name>
  <category>
   Handbags
  </category>
  <size>
   S
  </size>
  <color>
   Зеленый
  </color>
  <material>
   Хлопок
  </material>
  <price>
   852649
  </price>
  <rating>
   3.89
  </rating>
  <reviews>
   306370
  </reviews>
  <new>
   -
  </new>
  <sporty>
   no
  </sporty>
 </clothing>
</clothing-items>
